{
  "Response": {
    "doc": {
      "record": [
        {
          "recordID": "info:getty/object/208060",
          "PrimaryTitle": "Hong Kong",
          "MakerName": "Unknown, photographer",
          "Type": "Photographs",
          "Medium": "Albumen silver print",
          "Place": "Place Created: Hong Kong, China",
          "Date": "after May 1888",
          "Source": "J. Paul Getty Museum",
          "ObjectNumber": "84.XA.941.5.14",
          "Department": "Photographs",
          "Dimensions": "15.2 &times; 20.5 cm (6 &times; 8 1/16 in.)",
          "imageThumbURI": "http://www.getty.edu/museum/media/images/web/thumbnail/20806001.jpg",
          "recordLink": "http://www.getty.edu/art/collection/objects/189845/unknown-maker-hong-kong-after-may-1888/"
        },
        {
          "recordID": "info:getty/object/308090",
          "PrimaryTitle": "[View of Hong Kong]",
          "MakerName": "Felice Beato, photographer (English, born Italy, 1832 - 1909)",
          "Type": "Photographs",
          "Medium": "Albumen silver print",
          "Place": "Place Created: China",
          "Date": "March 1860",
          "Source": "J. Paul Getty Museum",
          "CreditLine": "Partial gift from the Wilson Centre for Photography",
          "ObjectNumber": "2007.26.209.5",
          "Department": "Photographs",
          "Dimensions": "18.3 x 28.1 cm (7 3/16 x 11 1/16 in.)",
          "Culture": "British",
          "imageThumbURI": "http://www.getty.edu/museum/media/images/web/thumbnail/30809001.jpg",
          "recordLink": "http://www.getty.edu/art/collection/objects/241932/felice-beato-view-of-hong-kong-british-march-1860/"
        },
        {
          "recordID": "info:getty/object/228592",
          "PrimaryTitle": "[Queen&#039;s Road looking west, Hong Kong]",
          "MakerName": "Unknown, photographer",
          "Type": "Photographs",
          "Medium": "Albumen silver print",
          "Place": "Place Created: Hong Kong, China",
          "Date": "1870 - 1880",
          "Source": "J. Paul Getty Museum",
          "ObjectNumber": "84.XO.1356.7",
          "Department": "Photographs",
          "Dimensions": "21.5 x 27 cm (8 7/16 x 10 5/8 in.)",
          "imageThumbURI": "http://www.getty.edu/museum/media/images/web/thumbnail/22859201.jpg",
          "recordLink": "http://www.getty.edu/art/collection/objects/208297/unknown-maker-queen&#039;s-road-looking-west-hong-kong-1870-1880/"
        },
        {
          "recordID": "info:getty/object/307507",
          "PrimaryTitle": "Panorama of Hong Kong, taken from Happy Valley",
          "MakerName": "Felice Beato, photographer (English, born Italy, 1832 - 1909) <br> Henry Hering, printer (British, 1814 - 1893)",
          "Type": "Photographs",
          "Medium": "Albumen silver print",
          "Place": "Place Created: Hong Kong, China",
          "Date": "1860",
          "Source": "J. Paul Getty Museum",
          "CreditLine": "Partial gift from the Wilson Centre for Photography",
          "ObjectNumber": "2007.26.198.2",
          "Department": "Photographs",
          "Dimensions": "Other: 23.1 x 28.9 cm (9 1/8 x 11 3/8 in.)",
          "Culture": "British",
          "imageThumbURI": "http://www.getty.edu/museum/media/images/web/thumbnail/30750701.jpg",
          "recordLink": "http://www.getty.edu/art/collection/objects/241349/felice-beato-henry-hering-panorama-of-hong-kong-taken-from-happy-valley-british-1860/"
        },
        {
          "recordID": "info:getty/object/51725",
          "PrimaryTitle": "Interior of the Salon of Mr. Victor Kresser, Director of the Hong Kong Bank",
          "MakerName": "John Thomson, photographer (Scottish, 1837 - 1921)",
          "Type": "Photographs",
          "Medium": "Albumen silver print",
          "Place": "Place Created: China <br> Place Depicted: Hong Kong",
          "Date": "about 1865",
          "Source": "J. Paul Getty Museum",
          "ObjectNumber": "84.XM.859.49",
          "Department": "Photographs",
          "Dimensions": "22.5 &times; 21.4 cm (8 7/8 &times; 8 7/16 in.)",
          "Culture": "British",
          "imageThumbURI": "http://www.getty.edu/museum/media/images/web/thumbnail/05172501.jpg",
          "recordLink": "http://www.getty.edu/art/collection/objects/45219/john-thomson-interior-of-the-salon-of-mr-victor-kresser-director-of-the-hong-kong-bank-british-about-1865/"
        },
        {
          "recordID": "info:getty/object/307506",
          "PrimaryTitle": "[Panorama of Hong Kong, showing the Fleet for North China Expedition]",
          "MakerName": "Felice Beato, photographer (English, born Italy, 1832 - 1909) <br> Henry Hering, printer (British, 1814 - 1893)",
          "Type": "Photographs",
          "Medium": "Albumen silver print",
          "Place": "Place Created: Hong Kong, China",
          "Date": "March 1, 1860",
          "Source": "J. Paul Getty Museum",
          "CreditLine": "Partial gift from the Wilson Centre for Photography",
          "ObjectNumber": "2007.26.198.1",
          "Department": "Photographs",
          "Dimensions": "Other: 23.7 &times; 28.3 cm (9 5/16 &times; 11 1/8 in.)",
          "Culture": "British",
          "imageThumbURI": "http://www.getty.edu/museum/media/images/web/thumbnail/30750601.jpg",
          "recordLink": "http://www.getty.edu/art/collection/objects/241348/felice-beato-henry-hering-panorama-of-hong-kong-showing-the-fleet-for-north-china-expedition-british-march-1-1860/"
        },
        {
          "recordID": "info:getty/object/308091",
          "PrimaryTitle": "[Modern Building and View of Hong Kong]",
          "MakerName": "Felice Beato, photographer (English, born Italy, 1832 - 1909)",
          "Type": "Photographs",
          "Medium": "Albumen silver print",
          "Place": "Place Created: China",
          "Date": "March 1860",
          "Source": "J. Paul Getty Museum",
          "CreditLine": "Partial gift from the Wilson Centre for Photography",
          "ObjectNumber": "2007.26.209.6",
          "Department": "Photographs",
          "Dimensions": "15.4 x 25.6 cm (6 1/16 x 10 1/16 in.)",
          "Culture": "British",
          "imageThumbURI": "http://www.getty.edu/museum/media/images/web/thumbnail/30809101.jpg",
          "recordLink": "http://www.getty.edu/art/collection/objects/241933/felice-beato-modern-building-and-view-of-hong-kong-british-march-1860/"
        },
        {
          "recordID": "info:getty/object/208058",
          "PrimaryTitle": "Hongkong from Harbour",
          "MakerName": "Unknown, photographer",
          "Type": "Photographs",
          "Medium": "Albumen silver print",
          "Place": "Place Created: Hong Kong, China",
          "Date": "1889",
          "Source": "J. Paul Getty Museum",
          "ObjectNumber": "84.XA.941.5.12",
          "Department": "Photographs",
          "Dimensions": "15.1 &times; 20.3 cm (5 15/16 &times; 8 in.)",
          "imageThumbURI": "http://www.getty.edu/museum/media/images/web/thumbnail/20805801.jpg",
          "recordLink": "http://www.getty.edu/art/collection/objects/189843/unknown-maker-hongkong-from-harbour-1889/"
        },
        {
          "recordID": "info:getty/object/208059",
          "PrimaryTitle": "Hongkong from Kennedy Road",
          "MakerName": "Unknown, photographer",
          "Type": "Photographs",
          "Medium": "Albumen silver print",
          "Place": "Place Created: Hong Kong, China",
          "Date": "1870s - 1880s",
          "Source": "J. Paul Getty Museum",
          "ObjectNumber": "84.XA.941.5.13",
          "Department": "Photographs",
          "Dimensions": "15.3 &times; 20.4 cm (6 &times; 8 1/16 in.)",
          "imageThumbURI": "http://www.getty.edu/museum/media/images/web/thumbnail/20805901.jpg",
          "recordLink": "http://www.getty.edu/art/collection/objects/189844/unknown-maker-hongkong-from-kennedy-road-1870s-1880s/"
        },
        {
          "recordID": "info:getty/object/111596",
          "PrimaryTitle": "[Tung Choon Pagoda]",
          "MakerName": "Felice Beato, photographer (English, born Italy, 1832 - 1909)",
          "Type": "Photographs",
          "Medium": "Albumen silver print",
          "Place": "Place Created: Hong Kong China Japan <br> Place Depicted: China",
          "Date": "September 23, 1860",
          "Source": "J. Paul Getty Museum",
          "ObjectNumber": "84.XO.1176.11",
          "Department": "Photographs",
          "Dimensions": "23.9 x 28.6 cm (9 7/16 x 11 1/4 in.)",
          "Culture": "British",
          "imageThumbURI": "http://www.getty.edu/museum/media/images/web/thumbnail/11159601.jpg",
          "recordLink": "http://www.getty.edu/art/collection/objects/104460/felice-beato-tung-choon-pagoda-british-september-23-1860/"
        },
        {
          "recordID": "info:getty/object/307508",
          "PrimaryTitle": "Panorama - First Arrival of Chinese Expeditionary Force",
          "MakerName": "Felice Beato, photographer (English, born Italy, 1832 - 1909) <br> Henry Hering, printer (British, 1814 - 1893)",
          "Type": "Photographs",
          "Medium": "Albumen silver print",
          "Place": "Place Created: China",
          "Date": "March 1860",
          "Source": "J. Paul Getty Museum",
          "CreditLine": "Partial gift from the Wilson Centre for Photography",
          "ObjectNumber": "2007.26.198.3",
          "Department": "Photographs",
          "Dimensions": "Other: 23.2 x 29.6 cm (9 1/8 x 11 5/8 in.)",
          "Culture": "British",
          "imageThumbURI": "http://www.getty.edu/museum/media/images/web/thumbnail/30750801.jpg",
          "recordLink": "http://www.getty.edu/art/collection/objects/241350/felice-beato-henry-hering-panorama-first-arrival-of-chinese-expeditionary-force-british-march-1860/"
        },
        {
          "recordID": "info:getty/object/307509",
          "PrimaryTitle": "Panorama - Odin Bay",
          "MakerName": "Felice Beato, photographer (English, born Italy, 1832 - 1909) <br> Henry Hering, printer (British, 1814 - 1893)",
          "Type": "Photographs",
          "Medium": "Albumen silver print",
          "Place": "Place Created: China",
          "Date": "negative June 21 - July 21, 1860; print 1862",
          "Source": "J. Paul Getty Museum",
          "CreditLine": "Partial gift from the Wilson Centre for Photography",
          "ObjectNumber": "2007.26.198.4",
          "Department": "Photographs",
          "Dimensions": "Other: 23.9 x 29 cm (9 7/16 x 11 7/16 in.)",
          "Culture": "British",
          "imageThumbURI": "http://www.getty.edu/museum/media/images/web/thumbnail/30750901.jpg",
          "recordLink": "http://www.getty.edu/art/collection/objects/241351/felice-beato-henry-hering-panorama-odin-bay-british-negative-june-21-july-21-1860-print-1862/"
        }
      ]
    }
  }
}
